SILK2/Tools/logger/__init__.py
SILK2/Tools/logger/logger.py
silk2.tools.logger-1.1.2.dist-info/LICENSE
silk2.tools.logger-1.1.2.dist-info/METADATA
silk2.tools.logger-1.1.2.dist-info/WHEEL
silk2.tools.logger-1.1.2.dist-info/top_level.txt
silk2.tools.logger-1.1.2.dist-info/RECORD
